hgpasteapp
