Metadata-Version: 1.0
Name: hgpasteapp
Version: 0.1.2
Summary: Simple wrapper to hgweb that has paster app_factory entrypoints.
Home-page: UNKNOWN
Author: Maries Ionel Cristian
Author-email: ionel.mc@gmail.com
License: UNKNOWN
Platform: UNKNOWN
